setup.py
RunRunner.egg-info/PKG-INFO
RunRunner.egg-info/SOURCES.txt
RunRunner.egg-info/dependency_links.txt
RunRunner.egg-info/requires.txt
RunRunner.egg-info/top_level.txt
runrunner/__init__.py
runrunner/base.py
runrunner/local.py
runrunner/logger.py
runrunner/slurm.py
runrunner/timing.py
runrunner/utils.py
test/test_timing.py