Metadata-Version: 2.4
Name: RunRunner
Version: 0.2.0.4
Summary: RunRunner is a wrapper library for creating and managing subprocesses and their status, mainly focussed on using Slurm but (in absence) can also work with local jobs.
Home-page: https://github.com/ADA-research/RunRunner
Author: Thijs Snelleman
Author-email: fkt_sparkle@aim.rwth-aachen.de
Requires-Dist: pydantic<2.0a
Dynamic: author
Dynamic: author-email
Dynamic: description
Dynamic: description-content-type
Dynamic: home-page
Dynamic: requires-dist
Dynamic: summary
